llfn/__init__.py
llfn/llfn.py
llfn-0.1.7.dist-info/LICENSE
llfn-0.1.7.dist-info/METADATA
llfn-0.1.7.dist-info/WHEEL
llfn-0.1.7.dist-info/RECORD
