Metadata-Version: 2.1
Name: llfn
Version: 0.1.7
Summary: Build anything from a simple text-summarizer to complex AI agents with one common primitive: function
Author: Sorawit Suriyakarn
Author-email: thepsint@gmail.com
Requires-Python: >=3.8.1,<4.0
Classifier: Programming Language :: Python :: 3
Classifier: Programming Language :: Python :: 3.9
Classifier: Programming Language :: Python :: 3.10
Classifier: Programming Language :: Python :: 3.11
Requires-Dist: langchain (>=0.0.1)
Requires-Dist: openai (>=0.27.0)
